BackcastPro/__init__.py
BackcastPro/_broker.py
BackcastPro/_stats.py
BackcastPro/backtest.py
BackcastPro/order.py
BackcastPro/position.py
BackcastPro/trade.py
BackcastPro/api/__init__.py
BackcastPro/api/board.py
BackcastPro/api/chart.py
BackcastPro/api/db_manager.py
BackcastPro/api/db_stocks_board.py
BackcastPro/api/db_stocks_daily.py
BackcastPro/api/db_stocks_info.py
BackcastPro/api/state_publisher.py
BackcastPro/api/stocks_board.py
BackcastPro/api/stocks_info.py
BackcastPro/api/stocks_price.py
BackcastPro/api/trade_event_publisher.py
BackcastPro/api/lib/__init__.py
BackcastPro/api/lib/e_api.py
BackcastPro/api/lib/jquants.py
BackcastPro/api/lib/kabusap.py
BackcastPro/api/lib/stooq.py
BackcastPro/api/lib/util.py
backcastpro-0.3.7.dist-info/METADATA
backcastpro-0.3.7.dist-info/WHEEL
backcastpro-0.3.7.dist-info/RECORD
