Metadata-Version: 2.4
Name: BackcastPro
Version: 0.3.7
Summary: トレーディング戦略のためのPythonバックテストライブラリ
Project-URL: Homepage, https://github.com/botterYosuke/BackcastPro/
Project-URL: Issues, https://github.com/botterYosuke/BackcastPro/issues
Project-URL: Logo, https://raw.githubusercontent.com/botterYosuke/BackcastPro/main/docs/img/logo.drawio.svg
Author: botterYosuke
Classifier: License :: OSI Approved :: MIT License
Classifier: Operating System :: OS Independent
Classifier: Programming Language :: Python :: 3
Classifier: Programming Language :: Python :: 3.9
Classifier: Programming Language :: Python :: 3.10
Classifier: Programming Language :: Python :: 3.11
Classifier: Programming Language :: Python :: 3.12
Requires-Python: >=3.9
Requires-Dist: anywidget>=0.9.21
Requires-Dist: duckdb>=0.9.0
Requires-Dist: matplotlib>=3.0.0
Requires-Dist: msgpack>=1.0.0
Requires-Dist: numpy>=1.20.0
Requires-Dist: pandas>=1.3.0
Requires-Dist: plotly>=5.0.0
Requires-Dist: python-dotenv>=0.19.0
Requires-Dist: requests>=2.25.0
Requires-Dist: scipy>=1.7.0
Provides-Extra: all
Requires-Dist: yfinance>=0.2.0; extra == 'all'
Provides-Extra: yfinance
Requires-Dist: yfinance>=0.2.0; extra == 'yfinance'
